setup.py
adspy/__init__.py
adspy/pyads.py
adspy.egg-info/PKG-INFO
adspy.egg-info/SOURCES.txt
adspy.egg-info/dependency_links.txt
adspy.egg-info/top_level.txt