Metadata-Version: 1.1
Name: adspy
Version: 0.1.0
Summary: Simple bibtex tools for use with ADS.
Home-page: UNKNOWN
Author: Samuel Skillman <samskillman@gmail.com>
Author-email: UNKNOWN
License: GPLv3
Keywords: data
Platform: UNKNOWN
Classifier: Programming Language :: Python
Classifier: Topic :: Software Development :: Libraries :: Python Modules
